p4s/__init__.py
p4s/core/__init__.py
p4s/core/constants.py
p4s/core/display.py
p4s/core/infer.py
p4s/core/logic.py
p4s/core/phivalue.py
p4s/core/stypes.py
p4s/dsl/__init__.py
p4s/dsl/backtick.py
p4s/semantics/__init__.py
p4s/semantics/ch3.py
p4s/semantics/interpret.py
p4s/simplify/__init__.py
p4s/simplify/guard_pass.py
p4s/simplify/lambda_pass.py
p4s/simplify/macro_pass.py
p4s/simplify/passes.py
p4s/simplify/utils.py
p4s/syntax/__init__.py
p4s/syntax/tree.py
p4s-0.4.4.dist-info/METADATA
p4s-0.4.4.dist-info/WHEEL
p4s-0.4.4.dist-info/top_level.txt
p4s-0.4.4.dist-info/RECORD
