Metadata-Version: 2.4
Name: p4s
Version: 0.4.4
Summary: Phosphorus: a lightweight semantics toolkit
Requires-Python: >=3.11
Requires-Dist: svgling
Requires-Dist: black
Requires-Dist: nltk
Requires-Dist: pygments
